{
    "routes": [
        {
            "id": "madinah-airport-to-makkah-hotel",
            "name": "Madinah Airport to Makkah Hotel",
            "slug": "madinah-airport-to-makkah",
            "seo": {
                "title": "Taxi Madinah Airport to Makkah | VIP Transfer | توصيل مطار المدينة مكة",
                "description": "Book trusted taxi from Madinah Airport to Makkah Hotel. VIP GMC Yukon & Staria available. 4.5 hour journey with Miqat stop. Starting from 450 SAR.",
                "keywords": [
                    "Madinah Airport to Makkah taxi",
                    "Madinah Airport taxi price",
                    "Taxi fare Madinah airport to Makkah",
                    "VIP transport Madinah to Makkah",
                    "GMC Yukon Madinah Airport",
                    "توصيل من مطار المدينة الى مكة",
                    "تاكسي مطار المدينة",
                    "سعر التوصيل من المدينة لمكة",
                    "حجز سيارة عائلية مكة",
                    "taxi from Madinah Airport to Makkah",
                    "Madinah Airport to Makkah fare",
                    "how much is taxi from Madinah Airport to Makkah",
                    "book cab Madinah Airport",
                    "transportation to Makkah",
                    "private car Madinah Airport to Makkah",
                    "book online Madinah Airport",
                    "Madinah Airport to Makkah book online",
                    "cheap transport Madinah Airport",
                    "Madinah Airport to Makkah cheap transport",
                    "affordable taxi Madinah Airport",
                    "Madinah Airport to Makkah affordable taxi",
                    "VIP transfer Madinah Airport",
                    "Madinah Airport to Makkah VIP transfer",
                    "luxury ride Madinah Airport",
                    "Madinah Airport to Makkah luxury ride",
                    "private cab Madinah Airport",
                    "Madinah Airport to Makkah private cab",
                    "reliable transportation Madinah Airport",
                    "Madinah Airport to Makkah reliable transportation",
                    "family van hire Madinah Airport",
                    "Madinah Airport to Makkah family van hire",
                    "group travel bus Madinah Airport",
                    "Madinah Airport to Makkah group travel bus",
                    "24/7 service Madinah Airport",
                    "Madinah Airport to Makkah 24/7 service",
                    "instant confirmation booking Madinah Airport",
                    "Madinah Airport to Makkah instant confirmation booking",
                    "whatsapp reservation Madinah Airport",
                    "Madinah Airport to Makkah whatsapp reservation",
                    "safe pilgrim travel Madinah Airport",
                    "Madinah Airport to Makkah safe pilgrim travel",
                    "executive chauffeur Madinah Airport",
                    "Madinah Airport to Makkah executive chauffeur",
                    "GMC Yukon XL Madinah Airport to Makkah",
                    "rent GMC Yukon XL in Makkah",
                    "Hyundai Staria VIP Madinah Airport to Makkah",
                    "rent Hyundai Staria VIP in Makkah",
                    "Toyota Camry sedan Madinah Airport to Makkah",
                    "rent Toyota Camry sedan in Makkah",
                    "Toyota Hiace bus Madinah Airport to Makkah",
                    "rent Toyota Hiace bus in Makkah",
                    "luxury SUV rental Madinah Airport to Makkah",
                    "rent luxury SUV rental in Makkah",
                    "7 seater family van Madinah Airport to Makkah",
                    "rent 7 seater family van in Makkah",
                    "11 passenger minibus Madinah Airport to Makkah",
                    "rent 11 passenger minibus in Makkah",
                    "premium VIP car Madinah Airport to Makkah",
                    "rent premium VIP car in Makkah",
                    "pilgrim transport Madinah Airport to Makkah",
                    "umrah taxi company Madinah Airport to Makkah",
                    "certified drivers Madinah Airport to Makkah",
                    "ihram friendly Madinah Airport to Makkah",
                    "saudi transport agency Madinah Airport to Makkah",
                    "hajj cab service Madinah Airport to Makkah",
                    "english speaking driver Madinah Airport to Makkah",
                    "Madinah Airport airport transfer",
                    "airport transfer to Makkah",
                    "Madinah Airport meet and greet",
                    "meet and greet to Makkah",
                    "Madinah Airport terminal pickup",
                    "terminal pickup to Makkah",
                    "Madinah Airport KAIA",
                    "KAIA to Makkah",
                    "Madinah Airport MED",
                    "MED to Makkah",
                    "Madinah Airport airport dropoff",
                    "airport dropoff to Makkah"
                ]
            },
            "distance": "450 km",
            "time": "4 hrs 30 min",
            "baseRate": 450,
            "customRates": {
                "camry": 450,
                "hiace": 550,
                "gmc": 900,
                "starex": 450,
                "staria": 450,
                "coaster": 900
            }
        },
        {
            "id": "692db09934f15bc89b45a5fd",
            "name": "Jeddah Airport to Makkah Hotel",
            "slug": "jeddah-airport-to-makkah",
            "seo": {
                "title": "Taxi Jeddah Airport to Makkah | VIP Umrah Transfer | تاكسي مطار جدة مكة",
                "description": "Best Taxi Jeddah Airport to Makkah. Official & licensed drivers. Luxury GMC, Staria & Camry. Meet & Greet at KAIA Terminal 1. Book now from 250 SAR.",
                "keywords": [
                    "Jeddah Airport to Makkah taxi",
                    "Jeddah airport transfer",
                    "Taxi fare Jeddah to Makkah",
                    "KAIA to Makkah harvest",
                    "Jeddah airport taxi booking",
                    "Umrah taxi service Jeddah",
                    "توصيل من مطار جدة الى مكة",
                    "تاكسي مطار جدة",
                    "سعر التاكسي من جدة للحرم",
                    "نقل معتمرين جدة مكة",
                    "كاديلك او جمس مطار جدة",
                    "taxi from Jeddah Airport to Makkah",
                    "Jeddah Airport to Makkah fare",
                    "how much is taxi from Jeddah Airport to Makkah",
                    "book cab Jeddah Airport",
                    "transportation to Makkah",
                    "private car Jeddah Airport to Makkah",
                    "book online Jeddah Airport",
                    "Jeddah Airport to Makkah book online",
                    "cheap transport Jeddah Airport",
                    "Jeddah Airport to Makkah cheap transport",
                    "affordable taxi Jeddah Airport",
                    "Jeddah Airport to Makkah affordable taxi",
                    "VIP transfer Jeddah Airport",
                    "Jeddah Airport to Makkah VIP transfer",
                    "luxury ride Jeddah Airport",
                    "Jeddah Airport to Makkah luxury ride",
                    "private cab Jeddah Airport",
                    "Jeddah Airport to Makkah private cab",
                    "reliable transportation Jeddah Airport",
                    "Jeddah Airport to Makkah reliable transportation",
                    "family van hire Jeddah Airport",
                    "Jeddah Airport to Makkah family van hire",
                    "group travel bus Jeddah Airport",
                    "Jeddah Airport to Makkah group travel bus",
                    "24/7 service Jeddah Airport",
                    "Jeddah Airport to Makkah 24/7 service",
                    "instant confirmation booking Jeddah Airport",
                    "Jeddah Airport to Makkah instant confirmation booking",
                    "whatsapp reservation Jeddah Airport",
                    "Jeddah Airport to Makkah whatsapp reservation",
                    "safe pilgrim travel Jeddah Airport",
                    "Jeddah Airport to Makkah safe pilgrim travel",
                    "executive chauffeur Jeddah Airport",
                    "Jeddah Airport to Makkah executive chauffeur",
                    "GMC Yukon XL Jeddah Airport to Makkah",
                    "rent GMC Yukon XL in Makkah",
                    "Hyundai Staria VIP Jeddah Airport to Makkah",
                    "rent Hyundai Staria VIP in Makkah",
                    "Toyota Camry sedan Jeddah Airport to Makkah",
                    "rent Toyota Camry sedan in Makkah",
                    "Toyota Hiace bus Jeddah Airport to Makkah",
                    "rent Toyota Hiace bus in Makkah",
                    "luxury SUV rental Jeddah Airport to Makkah",
                    "rent luxury SUV rental in Makkah",
                    "7 seater family van Jeddah Airport to Makkah",
                    "rent 7 seater family van in Makkah",
                    "11 passenger minibus Jeddah Airport to Makkah",
                    "rent 11 passenger minibus in Makkah",
                    "premium VIP car Jeddah Airport to Makkah",
                    "rent premium VIP car in Makkah",
                    "pilgrim transport Jeddah Airport to Makkah",
                    "umrah taxi company Jeddah Airport to Makkah",
                    "certified drivers Jeddah Airport to Makkah",
                    "ihram friendly Jeddah Airport to Makkah",
                    "saudi transport agency Jeddah Airport to Makkah",
                    "hajj cab service Jeddah Airport to Makkah",
                    "english speaking driver Jeddah Airport to Makkah",
                    "Jeddah Airport airport transfer",
                    "airport transfer to Makkah",
                    "Jeddah Airport meet and greet",
                    "meet and greet to Makkah",
                    "Jeddah Airport terminal pickup",
                    "terminal pickup to Makkah",
                    "Jeddah Airport KAIA",
                    "KAIA to Makkah",
                    "Jeddah Airport MED",
                    "MED to Makkah",
                    "Jeddah Airport airport dropoff",
                    "airport dropoff to Makkah"
                ]
            },
            "distance": "100 km",
            "time": "1 hr 30 min",
            "baseRate": 250,
            "customRates": {
                "camry": 250,
                "hiace": 350,
                "gmc": 500,
                "starex": 300,
                "staria": 300,
                "coaster": 550
            }
        },
        {
            "id": "madinah-ziyarat-wadi-jinn",
            "name": "Madinah Ziyarat Taxi and Wadi Jin",
            "slug": "madinah-ziyarat-wadi-jinn",
            "seo": {
                "title": "Madinah Ziyarat Tour & Wadi Jinn | Historical Places | مزارات المدينة",
                "description": "Comprehensive Ziyarat tour in Madinah including Wadi-e-Jinn, Ohud, Quba Mosque, Seven Mosques. Private AC car with local driver. 4-5 Hours tour.",
                "keywords": [
                    "Madinah Ziyarat places",
                    "Wadi Jinn Madinah tour",
                    "Ziyarat taxi Madinah",
                    "Masjid Quba taxi",
                    "Mount Ohud visit",
                    "historical places in Madinah",
                    "مزارات المدينة المنورة",
                    "وادي الجن",
                    "جولة سياحية المدينة",
                    "زيارة المساجد السبعة",
                    "Madinah Ziyarat Taxi and Wadi Jin to Saudi Arabia taxi",
                    "taxi from Madinah Ziyarat Taxi and Wadi Jin to Saudi Arabia",
                    "Madinah Ziyarat Taxi and Wadi Jin to Saudi Arabia fare",
                    "how much is taxi from Madinah Ziyarat Taxi and Wadi Jin to Saudi Arabia",
                    "book cab Madinah Ziyarat Taxi and Wadi Jin",
                    "transportation to Saudi Arabia",
                    "private car Madinah Ziyarat Taxi and Wadi Jin to Saudi Arabia",
                    "book online Madinah Ziyarat Taxi and Wadi Jin",
                    "Madinah Ziyarat Taxi and Wadi Jin to Saudi Arabia book online",
                    "cheap transport Madinah Ziyarat Taxi and Wadi Jin",
                    "Madinah Ziyarat Taxi and Wadi Jin to Saudi Arabia cheap transport",
                    "affordable taxi Madinah Ziyarat Taxi and Wadi Jin",
                    "Madinah Ziyarat Taxi and Wadi Jin to Saudi Arabia affordable taxi",
                    "VIP transfer Madinah Ziyarat Taxi and Wadi Jin",
                    "Madinah Ziyarat Taxi and Wadi Jin to Saudi Arabia VIP transfer",
                    "luxury ride Madinah Ziyarat Taxi and Wadi Jin",
                    "Madinah Ziyarat Taxi and Wadi Jin to Saudi Arabia luxury ride",
                    "private cab Madinah Ziyarat Taxi and Wadi Jin",
                    "Madinah Ziyarat Taxi and Wadi Jin to Saudi Arabia private cab",
                    "reliable transportation Madinah Ziyarat Taxi and Wadi Jin",
                    "Madinah Ziyarat Taxi and Wadi Jin to Saudi Arabia reliable transportation",
                    "family van hire Madinah Ziyarat Taxi and Wadi Jin",
                    "Madinah Ziyarat Taxi and Wadi Jin to Saudi Arabia family van hire",
                    "group travel bus Madinah Ziyarat Taxi and Wadi Jin",
                    "Madinah Ziyarat Taxi and Wadi Jin to Saudi Arabia group travel bus",
                    "24/7 service Madinah Ziyarat Taxi and Wadi Jin",
                    "Madinah Ziyarat Taxi and Wadi Jin to Saudi Arabia 24/7 service",
                    "instant confirmation booking Madinah Ziyarat Taxi and Wadi Jin",
                    "Madinah Ziyarat Taxi and Wadi Jin to Saudi Arabia instant confirmation booking",
                    "whatsapp reservation Madinah Ziyarat Taxi and Wadi Jin",
                    "Madinah Ziyarat Taxi and Wadi Jin to Saudi Arabia whatsapp reservation",
                    "safe pilgrim travel Madinah Ziyarat Taxi and Wadi Jin",
                    "Madinah Ziyarat Taxi and Wadi Jin to Saudi Arabia safe pilgrim travel",
                    "executive chauffeur Madinah Ziyarat Taxi and Wadi Jin",
                    "Madinah Ziyarat Taxi and Wadi Jin to Saudi Arabia executive chauffeur",
                    "GMC Yukon XL Madinah Ziyarat Taxi and Wadi Jin to Saudi Arabia",
                    "rent GMC Yukon XL in Saudi Arabia",
                    "Hyundai Staria VIP Madinah Ziyarat Taxi and Wadi Jin to Saudi Arabia",
                    "rent Hyundai Staria VIP in Saudi Arabia",
                    "Toyota Camry sedan Madinah Ziyarat Taxi and Wadi Jin to Saudi Arabia",
                    "rent Toyota Camry sedan in Saudi Arabia",
                    "Toyota Hiace bus Madinah Ziyarat Taxi and Wadi Jin to Saudi Arabia",
                    "rent Toyota Hiace bus in Saudi Arabia",
                    "luxury SUV rental Madinah Ziyarat Taxi and Wadi Jin to Saudi Arabia",
                    "rent luxury SUV rental in Saudi Arabia",
                    "7 seater family van Madinah Ziyarat Taxi and Wadi Jin to Saudi Arabia",
                    "rent 7 seater family van in Saudi Arabia",
                    "11 passenger minibus Madinah Ziyarat Taxi and Wadi Jin to Saudi Arabia",
                    "rent 11 passenger minibus in Saudi Arabia",
                    "premium VIP car Madinah Ziyarat Taxi and Wadi Jin to Saudi Arabia",
                    "rent premium VIP car in Saudi Arabia",
                    "pilgrim transport Madinah Ziyarat Taxi and Wadi Jin to Saudi Arabia",
                    "umrah taxi company Madinah Ziyarat Taxi and Wadi Jin to Saudi Arabia",
                    "certified drivers Madinah Ziyarat Taxi and Wadi Jin to Saudi Arabia",
                    "ihram friendly Madinah Ziyarat Taxi and Wadi Jin to Saudi Arabia",
                    "saudi transport agency Madinah Ziyarat Taxi and Wadi Jin to Saudi Arabia",
                    "hajj cab service Madinah Ziyarat Taxi and Wadi Jin to Saudi Arabia",
                    "english speaking driver Madinah Ziyarat Taxi and Wadi Jin to Saudi Arabia",
                    "historical tour Madinah Ziyarat Taxi and Wadi Jin",
                    "Madinah Ziyarat Taxi and Wadi Jin historical tour taxi",
                    "islamic landmarks Madinah Ziyarat Taxi and Wadi Jin",
                    "Madinah Ziyarat Taxi and Wadi Jin islamic landmarks taxi",
                    "cave hira Madinah Ziyarat Taxi and Wadi Jin",
                    "Madinah Ziyarat Taxi and Wadi Jin cave hira taxi",
                    "mount uhud Madinah Ziyarat Taxi and Wadi Jin",
                    "Madinah Ziyarat Taxi and Wadi Jin mount uhud taxi",
                    "masjid quba Madinah Ziyarat Taxi and Wadi Jin",
                    "Madinah Ziyarat Taxi and Wadi Jin masjid quba taxi",
                    "private guide Madinah Ziyarat Taxi and Wadi Jin",
                    "Madinah Ziyarat Taxi and Wadi Jin private guide taxi",
                    "ziyarat package Madinah Ziyarat Taxi and Wadi Jin",
                    "Madinah Ziyarat Taxi and Wadi Jin ziyarat package taxi",
                    "jabal thawr Madinah Ziyarat Taxi and Wadi Jin",
                    "Madinah Ziyarat Taxi and Wadi Jin jabal thawr taxi",
                    "qiblatayn Madinah Ziyarat Taxi and Wadi Jin",
                    "Madinah Ziyarat Taxi and Wadi Jin qiblatayn taxi",
                    "seven mosques Madinah Ziyarat Taxi and Wadi Jin",
                    "Madinah Ziyarat Taxi and Wadi Jin seven mosques taxi"
                ]
            },
            "distance": "50 km",
            "time": "4-5 hrs",
            "baseRate": 300,
            "customRates": {
                "camry": 300,
                "hiace": 350,
                "gmc": 500,
                "starex": 350,
                "staria": 350,
                "coaster": 600
            }
        },
        {
            "id": "692db09934f15bc89b45a601",
            "name": "Makkah Hotel to Jeddah Airport",
            "slug": "makkah-to-jeddah-airport",
            "seo": {
                "title": "Taxi Makkah to Jeddah Airport | Reliable Departure | توصيل مكة للمطار",
                "description": "Guaranteed pickup from your Makkah hotel to Jeddah Airport (KAIA). Punctual drivers, 24/7 service. Ensure you catch your flight on time. From 200 SAR.",
                "keywords": [
                    "Makkah to Jeddah Airport taxi",
                    "Makkah to KAIA taxi",
                    "Taxi Makkah to Jeddah Terminal 1",
                    "Makkah hotel to airport transfer",
                    "cheap taxi Makkah to Jeddah",
                    "توصيل من مكة للمطار",
                    "تاكسي مكة جدة",
                    "نقل من فندق مكة للمطار",
                    "حجز تكسي مكة",
                    "taxi from Makkah to Jeddah Airport",
                    "Makkah to Jeddah Airport fare",
                    "how much is taxi from Makkah to Jeddah Airport",
                    "book cab Makkah",
                    "transportation to Jeddah Airport",
                    "private car Makkah to Jeddah Airport",
                    "book online Makkah",
                    "Makkah to Jeddah Airport book online",
                    "cheap transport Makkah",
                    "Makkah to Jeddah Airport cheap transport",
                    "affordable taxi Makkah",
                    "Makkah to Jeddah Airport affordable taxi",
                    "VIP transfer Makkah",
                    "Makkah to Jeddah Airport VIP transfer",
                    "luxury ride Makkah",
                    "Makkah to Jeddah Airport luxury ride",
                    "private cab Makkah",
                    "Makkah to Jeddah Airport private cab",
                    "reliable transportation Makkah",
                    "Makkah to Jeddah Airport reliable transportation",
                    "family van hire Makkah",
                    "Makkah to Jeddah Airport family van hire",
                    "group travel bus Makkah",
                    "Makkah to Jeddah Airport group travel bus",
                    "24/7 service Makkah",
                    "Makkah to Jeddah Airport 24/7 service",
                    "instant confirmation booking Makkah",
                    "Makkah to Jeddah Airport instant confirmation booking",
                    "whatsapp reservation Makkah",
                    "Makkah to Jeddah Airport whatsapp reservation",
                    "safe pilgrim travel Makkah",
                    "Makkah to Jeddah Airport safe pilgrim travel",
                    "executive chauffeur Makkah",
                    "Makkah to Jeddah Airport executive chauffeur",
                    "GMC Yukon XL Makkah to Jeddah Airport",
                    "rent GMC Yukon XL in Jeddah Airport",
                    "Hyundai Staria VIP Makkah to Jeddah Airport",
                    "rent Hyundai Staria VIP in Jeddah Airport",
                    "Toyota Camry sedan Makkah to Jeddah Airport",
                    "rent Toyota Camry sedan in Jeddah Airport",
                    "Toyota Hiace bus Makkah to Jeddah Airport",
                    "rent Toyota Hiace bus in Jeddah Airport",
                    "luxury SUV rental Makkah to Jeddah Airport",
                    "rent luxury SUV rental in Jeddah Airport",
                    "7 seater family van Makkah to Jeddah Airport",
                    "rent 7 seater family van in Jeddah Airport",
                    "11 passenger minibus Makkah to Jeddah Airport",
                    "rent 11 passenger minibus in Jeddah Airport",
                    "premium VIP car Makkah to Jeddah Airport",
                    "rent premium VIP car in Jeddah Airport",
                    "pilgrim transport Makkah to Jeddah Airport",
                    "umrah taxi company Makkah to Jeddah Airport",
                    "certified drivers Makkah to Jeddah Airport",
                    "ihram friendly Makkah to Jeddah Airport",
                    "saudi transport agency Makkah to Jeddah Airport",
                    "hajj cab service Makkah to Jeddah Airport",
                    "english speaking driver Makkah to Jeddah Airport",
                    "Makkah airport transfer",
                    "airport transfer to Jeddah Airport",
                    "Makkah meet and greet",
                    "meet and greet to Jeddah Airport",
                    "Makkah terminal pickup",
                    "terminal pickup to Jeddah Airport",
                    "Makkah KAIA",
                    "KAIA to Jeddah Airport",
                    "Makkah MED",
                    "MED to Jeddah Airport",
                    "Makkah airport dropoff",
                    "airport dropoff to Jeddah Airport"
                ]
            },
            "distance": "100 km",
            "time": "1 hr 30 min",
            "baseRate": 200,
            "customRates": {
                "camry": 200,
                "hiace": 350,
                "gmc": 500,
                "starex": 300,
                "staria": 300,
                "coaster": 550
            }
        },
        {
            "id": "692db09934f15bc89b45a5ff",
            "name": "Makkah Hotel to Madinah Hotel",
            "slug": "makkah-to-madinah-taxi",
            "seo": {
                "title": "Makkah to Madinah Taxi Price | VIP Private Car | توصيل مكة المدينة",
                "description": "Comfortable private taxi from Makkah to Madinah. 4.5 hour journey in luxury GMC or Staria. Request Miqat stop. Book online now starting 450 SAR.",
                "keywords": [
                    "Makkah to Madinah taxi fare",
                    "Makkah to Madinah car rental",
                    "Private car Makkah to Madinah",
                    "VIP transport Makkah Madinah",
                    "taxi fare Makkah to Madinah",
                    "توصيل من مكة الى المدينة",
                    "سعر التوصيل من مكة للمدينة",
                    "سيارة خاصة مكة المدينة",
                    "نقل عفش وركاب مكة المدينة",
                    "Makkah to Madinah taxi",
                    "taxi from Makkah to Madinah",
                    "Makkah to Madinah fare",
                    "how much is taxi from Makkah to Madinah",
                    "book cab Makkah",
                    "transportation to Madinah",
                    "private car Makkah to Madinah",
                    "book online Makkah",
                    "Makkah to Madinah book online",
                    "cheap transport Makkah",
                    "Makkah to Madinah cheap transport",
                    "affordable taxi Makkah",
                    "Makkah to Madinah affordable taxi",
                    "VIP transfer Makkah",
                    "Makkah to Madinah VIP transfer",
                    "luxury ride Makkah",
                    "Makkah to Madinah luxury ride",
                    "private cab Makkah",
                    "Makkah to Madinah private cab",
                    "reliable transportation Makkah",
                    "Makkah to Madinah reliable transportation",
                    "family van hire Makkah",
                    "Makkah to Madinah family van hire",
                    "group travel bus Makkah",
                    "Makkah to Madinah group travel bus",
                    "24/7 service Makkah",
                    "Makkah to Madinah 24/7 service",
                    "instant confirmation booking Makkah",
                    "Makkah to Madinah instant confirmation booking",
                    "whatsapp reservation Makkah",
                    "Makkah to Madinah whatsapp reservation",
                    "safe pilgrim travel Makkah",
                    "Makkah to Madinah safe pilgrim travel",
                    "executive chauffeur Makkah",
                    "Makkah to Madinah executive chauffeur",
                    "GMC Yukon XL Makkah to Madinah",
                    "rent GMC Yukon XL in Madinah",
                    "Hyundai Staria VIP Makkah to Madinah",
                    "rent Hyundai Staria VIP in Madinah",
                    "Toyota Camry sedan Makkah to Madinah",
                    "rent Toyota Camry sedan in Madinah",
                    "Toyota Hiace bus Makkah to Madinah",
                    "rent Toyota Hiace bus in Madinah",
                    "luxury SUV rental Makkah to Madinah",
                    "rent luxury SUV rental in Madinah",
                    "7 seater family van Makkah to Madinah",
                    "rent 7 seater family van in Madinah",
                    "11 passenger minibus Makkah to Madinah",
                    "rent 11 passenger minibus in Madinah",
                    "premium VIP car Makkah to Madinah",
                    "rent premium VIP car in Madinah",
                    "pilgrim transport Makkah to Madinah",
                    "umrah taxi company Makkah to Madinah",
                    "certified drivers Makkah to Madinah",
                    "ihram friendly Makkah to Madinah",
                    "saudi transport agency Makkah to Madinah",
                    "hajj cab service Makkah to Madinah",
                    "english speaking driver Makkah to Madinah"
                ]
            },
            "distance": "450 km",
            "time": "4 hrs 30 min",
            "baseRate": 450,
            "customRates": {
                "camry": 450,
                "hiace": 550,
                "gmc": 900,
                "starex": 450,
                "staria": 450,
                "coaster": 900
            }
        },
        {
            "id": "692db09934f15bc89b45a60e",
            "name": "Makkah/Madinah Hotel to Hourly Rental",
            "slug": "hourly-rental-makkah-madinah",
            "seo": {
                "title": "Hourly Car Rental with Driver Makkah & Madinah | Rent per Hour",
                "description": "Flexible hourly car rental with driver in Makkah or Madinah. Perfect for shopping, business meetings, or custom Ziyarat. Minimum 4 hours booking.",
                "keywords": [
                    "hourly car rental Makkah",
                    "rent car with driver Makkah",
                    "chauffeur service Madinah",
                    "car rental by hour Saudi Arabia",
                    "ايجار سيارة بالساعة مكة",
                    "سائق خاص بالساعة المدينة",
                    "Makkah/Madinah to Hourly Rental taxi",
                    "taxi from Makkah/Madinah to Hourly Rental",
                    "Makkah/Madinah to Hourly Rental fare",
                    "how much is taxi from Makkah/Madinah to Hourly Rental",
                    "book cab Makkah/Madinah",
                    "transportation to Hourly Rental",
                    "private car Makkah/Madinah to Hourly Rental",
                    "book online Makkah/Madinah",
                    "Makkah/Madinah to Hourly Rental book online",
                    "cheap transport Makkah/Madinah",
                    "Makkah/Madinah to Hourly Rental cheap transport",
                    "affordable taxi Makkah/Madinah",
                    "Makkah/Madinah to Hourly Rental affordable taxi",
                    "VIP transfer Makkah/Madinah",
                    "Makkah/Madinah to Hourly Rental VIP transfer",
                    "luxury ride Makkah/Madinah",
                    "Makkah/Madinah to Hourly Rental luxury ride",
                    "private cab Makkah/Madinah",
                    "Makkah/Madinah to Hourly Rental private cab",
                    "reliable transportation Makkah/Madinah",
                    "Makkah/Madinah to Hourly Rental reliable transportation",
                    "family van hire Makkah/Madinah",
                    "Makkah/Madinah to Hourly Rental family van hire",
                    "group travel bus Makkah/Madinah",
                    "Makkah/Madinah to Hourly Rental group travel bus",
                    "24/7 service Makkah/Madinah",
                    "Makkah/Madinah to Hourly Rental 24/7 service",
                    "instant confirmation booking Makkah/Madinah",
                    "Makkah/Madinah to Hourly Rental instant confirmation booking",
                    "whatsapp reservation Makkah/Madinah",
                    "Makkah/Madinah to Hourly Rental whatsapp reservation",
                    "safe pilgrim travel Makkah/Madinah",
                    "Makkah/Madinah to Hourly Rental safe pilgrim travel",
                    "executive chauffeur Makkah/Madinah",
                    "Makkah/Madinah to Hourly Rental executive chauffeur",
                    "GMC Yukon XL Makkah/Madinah to Hourly Rental",
                    "rent GMC Yukon XL in Hourly Rental",
                    "Hyundai Staria VIP Makkah/Madinah to Hourly Rental",
                    "rent Hyundai Staria VIP in Hourly Rental",
                    "Toyota Camry sedan Makkah/Madinah to Hourly Rental",
                    "rent Toyota Camry sedan in Hourly Rental",
                    "Toyota Hiace bus Makkah/Madinah to Hourly Rental",
                    "rent Toyota Hiace bus in Hourly Rental",
                    "luxury SUV rental Makkah/Madinah to Hourly Rental",
                    "rent luxury SUV rental in Hourly Rental",
                    "7 seater family van Makkah/Madinah to Hourly Rental",
                    "rent 7 seater family van in Hourly Rental",
                    "11 passenger minibus Makkah/Madinah to Hourly Rental",
                    "rent 11 passenger minibus in Hourly Rental",
                    "premium VIP car Makkah/Madinah to Hourly Rental",
                    "rent premium VIP car in Hourly Rental",
                    "pilgrim transport Makkah/Madinah to Hourly Rental",
                    "umrah taxi company Makkah/Madinah to Hourly Rental",
                    "certified drivers Makkah/Madinah to Hourly Rental",
                    "ihram friendly Makkah/Madinah to Hourly Rental",
                    "saudi transport agency Makkah/Madinah to Hourly Rental",
                    "hajj cab service Makkah/Madinah to Hourly Rental",
                    "english speaking driver Makkah/Madinah to Hourly Rental"
                ]
            },
            "distance": "-",
            "time": "1 Hour",
            "baseRate": 80,
            "customRates": {
                "camry": 80,
                "hiace": 120,
                "gmc": 140,
                "starex": 100,
                "staria": 100,
                "coaster": 250
            }
        },
        {
            "id": "692db09a34f15bc89b45a60b",
            "name": "Makkah Hotel to Taif and Return",
            "slug": "makkah-to-taif-taxi",
            "seo": {
                "title": "Taxi Makkah to Taif Tour | Cable Car & Return | توصيل مكة الطائف",
                "description": "Enjoy a day trip from Makkah to Taif. Visit Cable Car (Telefric), Rose Factories, and Museums. Full day round trip with waiting. From 500 SAR.",
                "keywords": [
                    "Makkah to Taif taxi",
                    "Taif tour from Makkah",
                    "Makkah to Taif teleferic",
                    "Taif city tour",
                    "رحلة الطائف من مكة",
                    "تاكسي مكة الطائف",
                    "توصيل مكة الهدا",
                    "Makkah to Taif and Return taxi",
                    "taxi from Makkah to Taif and Return",
                    "Makkah to Taif and Return fare",
                    "how much is taxi from Makkah to Taif and Return",
                    "book cab Makkah",
                    "transportation to Taif and Return",
                    "private car Makkah to Taif and Return",
                    "book online Makkah",
                    "Makkah to Taif and Return book online",
                    "cheap transport Makkah",
                    "Makkah to Taif and Return cheap transport",
                    "affordable taxi Makkah",
                    "Makkah to Taif and Return affordable taxi",
                    "VIP transfer Makkah",
                    "Makkah to Taif and Return VIP transfer",
                    "luxury ride Makkah",
                    "Makkah to Taif and Return luxury ride",
                    "private cab Makkah",
                    "Makkah to Taif and Return private cab",
                    "reliable transportation Makkah",
                    "Makkah to Taif and Return reliable transportation",
                    "family van hire Makkah",
                    "Makkah to Taif and Return family van hire",
                    "group travel bus Makkah",
                    "Makkah to Taif and Return group travel bus",
                    "24/7 service Makkah",
                    "Makkah to Taif and Return 24/7 service",
                    "instant confirmation booking Makkah",
                    "Makkah to Taif and Return instant confirmation booking",
                    "whatsapp reservation Makkah",
                    "Makkah to Taif and Return whatsapp reservation",
                    "safe pilgrim travel Makkah",
                    "Makkah to Taif and Return safe pilgrim travel",
                    "executive chauffeur Makkah",
                    "Makkah to Taif and Return executive chauffeur",
                    "GMC Yukon XL Makkah to Taif and Return",
                    "rent GMC Yukon XL in Taif and Return",
                    "Hyundai Staria VIP Makkah to Taif and Return",
                    "rent Hyundai Staria VIP in Taif and Return",
                    "Toyota Camry sedan Makkah to Taif and Return",
                    "rent Toyota Camry sedan in Taif and Return",
                    "Toyota Hiace bus Makkah to Taif and Return",
                    "rent Toyota Hiace bus in Taif and Return",
                    "luxury SUV rental Makkah to Taif and Return",
                    "rent luxury SUV rental in Taif and Return",
                    "7 seater family van Makkah to Taif and Return",
                    "rent 7 seater family van in Taif and Return",
                    "11 passenger minibus Makkah to Taif and Return",
                    "rent 11 passenger minibus in Taif and Return",
                    "premium VIP car Makkah to Taif and Return",
                    "rent premium VIP car in Taif and Return",
                    "pilgrim transport Makkah to Taif and Return",
                    "umrah taxi company Makkah to Taif and Return",
                    "certified drivers Makkah to Taif and Return",
                    "ihram friendly Makkah to Taif and Return",
                    "saudi transport agency Makkah to Taif and Return",
                    "hajj cab service Makkah to Taif and Return",
                    "english speaking driver Makkah to Taif and Return"
                ]
            },
            "distance": "180 km",
            "time": "8-10 hrs",
            "baseRate": 500,
            "customRates": {
                "camry": 500,
                "hiace": 550,
                "gmc": 800,
                "starex": 450,
                "staria": 450,
                "coaster": 900
            }
        },
        {
            "id": "692db09a34f15bc89b45a60c",
            "name": "Jeddah Hotel to Taif and Return",
            "slug": "jeddah-to-taif-taxi",
            "seo": {
                "title": "Taxi Jeddah to Taif | Private Day Trip | توصيل جدة الطائف",
                "description": "Private taxi from Jeddah to Taif. Experience the cool weather of Taif, Al Hada mountain road, and fruit markets. One way or round trip available.",
                "keywords": [
                    "Jeddah to Taif taxi",
                    "Jeddah Taif airport transfer",
                    "Taxi fare Jeddah to Taif",
                    "visit Taif from Jeddah",
                    "توصيل جدة الطائف",
                    "مشوار جدة الطائف",
                    "تاكسي المطار للطائف",
                    "Jeddah to Taif and Return taxi",
                    "taxi from Jeddah to Taif and Return",
                    "Jeddah to Taif and Return fare",
                    "how much is taxi from Jeddah to Taif and Return",
                    "book cab Jeddah",
                    "transportation to Taif and Return",
                    "private car Jeddah to Taif and Return",
                    "book online Jeddah",
                    "Jeddah to Taif and Return book online",
                    "cheap transport Jeddah",
                    "Jeddah to Taif and Return cheap transport",
                    "affordable taxi Jeddah",
                    "Jeddah to Taif and Return affordable taxi",
                    "VIP transfer Jeddah",
                    "Jeddah to Taif and Return VIP transfer",
                    "luxury ride Jeddah",
                    "Jeddah to Taif and Return luxury ride",
                    "private cab Jeddah",
                    "Jeddah to Taif and Return private cab",
                    "reliable transportation Jeddah",
                    "Jeddah to Taif and Return reliable transportation",
                    "family van hire Jeddah",
                    "Jeddah to Taif and Return family van hire",
                    "group travel bus Jeddah",
                    "Jeddah to Taif and Return group travel bus",
                    "24/7 service Jeddah",
                    "Jeddah to Taif and Return 24/7 service",
                    "instant confirmation booking Jeddah",
                    "Jeddah to Taif and Return instant confirmation booking",
                    "whatsapp reservation Jeddah",
                    "Jeddah to Taif and Return whatsapp reservation",
                    "safe pilgrim travel Jeddah",
                    "Jeddah to Taif and Return safe pilgrim travel",
                    "executive chauffeur Jeddah",
                    "Jeddah to Taif and Return executive chauffeur",
                    "GMC Yukon XL Jeddah to Taif and Return",
                    "rent GMC Yukon XL in Taif and Return",
                    "Hyundai Staria VIP Jeddah to Taif and Return",
                    "rent Hyundai Staria VIP in Taif and Return",
                    "Toyota Camry sedan Jeddah to Taif and Return",
                    "rent Toyota Camry sedan in Taif and Return",
                    "Toyota Hiace bus Jeddah to Taif and Return",
                    "rent Toyota Hiace bus in Taif and Return",
                    "luxury SUV rental Jeddah to Taif and Return",
                    "rent luxury SUV rental in Taif and Return",
                    "7 seater family van Jeddah to Taif and Return",
                    "rent 7 seater family van in Taif and Return",
                    "11 passenger minibus Jeddah to Taif and Return",
                    "rent 11 passenger minibus in Taif and Return",
                    "premium VIP car Jeddah to Taif and Return",
                    "rent premium VIP car in Taif and Return",
                    "pilgrim transport Jeddah to Taif and Return",
                    "umrah taxi company Jeddah to Taif and Return",
                    "certified drivers Jeddah to Taif and Return",
                    "ihram friendly Jeddah to Taif and Return",
                    "saudi transport agency Jeddah to Taif and Return",
                    "hajj cab service Jeddah to Taif and Return",
                    "english speaking driver Jeddah to Taif and Return"
                ]
            },
            "distance": "350 km",
            "time": "10-12 hrs",
            "baseRate": 700,
            "customRates": {
                "camry": 700,
                "hiace": 700,
                "gmc": 1000,
                "starex": 600,
                "staria": 600,
                "coaster": 1000
            }
        },
        {
            "id": "6949b367a41f6410e88ed72e",
            "name": "Madinah Hotel to Madinah Ziyarat",
            "slug": "madinah-ziyarat-taxi",
            "seo": {
                "title": "Madinah Ziyarat Taxi Service | Visit Holy Places | مزارات المدينة",
                "description": "Book Madinah Ziyarat taxi to visit Masjid Quba, Qiblatun, Khandaq, and Mount Uhud. 3-4 hour spiritual tour with knowledgable local driver.",
                "keywords": [
                    "Madinah Ziyarat taxi",
                    "Madinah ziyarat tour price",
                    "places to visit in Madinah",
                    "ziyarat taxi package",
                    "Masjid Quba transport",
                    "مزارات المدينة المنورة",
                    "جولة مزارات",
                    "زيارة سيد الشهداء",
                    "Madinah to Madinah Ziyarat taxi",
                    "taxi from Madinah to Madinah Ziyarat",
                    "Madinah to Madinah Ziyarat fare",
                    "how much is taxi from Madinah to Madinah Ziyarat",
                    "book cab Madinah",
                    "transportation to Madinah Ziyarat",
                    "private car Madinah to Madinah Ziyarat",
                    "book online Madinah",
                    "Madinah to Madinah Ziyarat book online",
                    "cheap transport Madinah",
                    "Madinah to Madinah Ziyarat cheap transport",
                    "affordable taxi Madinah",
                    "Madinah to Madinah Ziyarat affordable taxi",
                    "VIP transfer Madinah",
                    "Madinah to Madinah Ziyarat VIP transfer",
                    "luxury ride Madinah",
                    "Madinah to Madinah Ziyarat luxury ride",
                    "private cab Madinah",
                    "Madinah to Madinah Ziyarat private cab",
                    "reliable transportation Madinah",
                    "Madinah to Madinah Ziyarat reliable transportation",
                    "family van hire Madinah",
                    "Madinah to Madinah Ziyarat family van hire",
                    "group travel bus Madinah",
                    "Madinah to Madinah Ziyarat group travel bus",
                    "24/7 service Madinah",
                    "Madinah to Madinah Ziyarat 24/7 service",
                    "instant confirmation booking Madinah",
                    "Madinah to Madinah Ziyarat instant confirmation booking",
                    "whatsapp reservation Madinah",
                    "Madinah to Madinah Ziyarat whatsapp reservation",
                    "safe pilgrim travel Madinah",
                    "Madinah to Madinah Ziyarat safe pilgrim travel",
                    "executive chauffeur Madinah",
                    "Madinah to Madinah Ziyarat executive chauffeur",
                    "GMC Yukon XL Madinah to Madinah Ziyarat",
                    "rent GMC Yukon XL in Madinah Ziyarat",
                    "Hyundai Staria VIP Madinah to Madinah Ziyarat",
                    "rent Hyundai Staria VIP in Madinah Ziyarat",
                    "Toyota Camry sedan Madinah to Madinah Ziyarat",
                    "rent Toyota Camry sedan in Madinah Ziyarat",
                    "Toyota Hiace bus Madinah to Madinah Ziyarat",
                    "rent Toyota Hiace bus in Madinah Ziyarat",
                    "luxury SUV rental Madinah to Madinah Ziyarat",
                    "rent luxury SUV rental in Madinah Ziyarat",
                    "7 seater family van Madinah to Madinah Ziyarat",
                    "rent 7 seater family van in Madinah Ziyarat",
                    "11 passenger minibus Madinah to Madinah Ziyarat",
                    "rent 11 passenger minibus in Madinah Ziyarat",
                    "premium VIP car Madinah to Madinah Ziyarat",
                    "rent premium VIP car in Madinah Ziyarat",
                    "pilgrim transport Madinah to Madinah Ziyarat",
                    "umrah taxi company Madinah to Madinah Ziyarat",
                    "certified drivers Madinah to Madinah Ziyarat",
                    "ihram friendly Madinah to Madinah Ziyarat",
                    "saudi transport agency Madinah to Madinah Ziyarat",
                    "hajj cab service Madinah to Madinah Ziyarat",
                    "english speaking driver Madinah to Madinah Ziyarat",
                    "historical tour Madinah",
                    "Madinah historical tour taxi",
                    "islamic landmarks Madinah",
                    "Madinah islamic landmarks taxi",
                    "cave hira Madinah",
                    "Madinah cave hira taxi",
                    "mount uhud Madinah",
                    "Madinah mount uhud taxi",
                    "masjid quba Madinah",
                    "Madinah masjid quba taxi",
                    "private guide Madinah",
                    "Madinah private guide taxi",
                    "ziyarat package Madinah",
                    "Madinah ziyarat package taxi",
                    "jabal thawr Madinah",
                    "Madinah jabal thawr taxi",
                    "qiblatayn Madinah",
                    "Madinah qiblatayn taxi",
                    "seven mosques Madinah",
                    "Madinah seven mosques taxi"
                ]
            },
            "distance": "40 km",
            "time": "3-4 hrs",
            "baseRate": 250,
            "customRates": {
                "camry": 250,
                "hiace": 250,
                "gmc": 400,
                "starex": 200,
                "staria": 200,
                "coaster": 500
            }
        },
        {
            "id": "6949b368a41f6410e88ed732",
            "name": "Makkah Hotel to Makkah Ziyarat",
            "slug": "makkah-ziyarat-taxi",
            "seo": {
                "title": "Makkah Ziyarat Taxi Tour | Hira Cave, Thawr & Arafat | مزارات مكة",
                "description": "Private taxi for Makkah Ziyarat. Visit Jabal Al-Nour (Hira Cave), Thawr, Arafat, Mina, and Muzdalifah. 3-4 hour comprehensive historical tour.",
                "keywords": [
                    "Makkah Ziyarat taxi",
                    "Ziyarat places Makkah",
                    "Hira cave taxi",
                    "Pillar of Jamarat tour",
                    "Makkah holy sites transport",
                    "مزارات مكة المكرمة",
                    "جولة المشاعر المقدسة",
                    "زيارة جبل النور",
                    "زيارة عرفات ومزدلفة",
                    "Makkah to Makkah Ziyarat taxi",
                    "taxi from Makkah to Makkah Ziyarat",
                    "Makkah to Makkah Ziyarat fare",
                    "how much is taxi from Makkah to Makkah Ziyarat",
                    "book cab Makkah",
                    "transportation to Makkah Ziyarat",
                    "private car Makkah to Makkah Ziyarat",
                    "book online Makkah",
                    "Makkah to Makkah Ziyarat book online",
                    "cheap transport Makkah",
                    "Makkah to Makkah Ziyarat cheap transport",
                    "affordable taxi Makkah",
                    "Makkah to Makkah Ziyarat affordable taxi",
                    "VIP transfer Makkah",
                    "Makkah to Makkah Ziyarat VIP transfer",
                    "luxury ride Makkah",
                    "Makkah to Makkah Ziyarat luxury ride",
                    "private cab Makkah",
                    "Makkah to Makkah Ziyarat private cab",
                    "reliable transportation Makkah",
                    "Makkah to Makkah Ziyarat reliable transportation",
                    "family van hire Makkah",
                    "Makkah to Makkah Ziyarat family van hire",
                    "group travel bus Makkah",
                    "Makkah to Makkah Ziyarat group travel bus",
                    "24/7 service Makkah",
                    "Makkah to Makkah Ziyarat 24/7 service",
                    "instant confirmation booking Makkah",
                    "Makkah to Makkah Ziyarat instant confirmation booking",
                    "whatsapp reservation Makkah",
                    "Makkah to Makkah Ziyarat whatsapp reservation",
                    "safe pilgrim travel Makkah",
                    "Makkah to Makkah Ziyarat safe pilgrim travel",
                    "executive chauffeur Makkah",
                    "Makkah to Makkah Ziyarat executive chauffeur",
                    "GMC Yukon XL Makkah to Makkah Ziyarat",
                    "rent GMC Yukon XL in Makkah Ziyarat",
                    "Hyundai Staria VIP Makkah to Makkah Ziyarat",
                    "rent Hyundai Staria VIP in Makkah Ziyarat",
                    "Toyota Camry sedan Makkah to Makkah Ziyarat",
                    "rent Toyota Camry sedan in Makkah Ziyarat",
                    "Toyota Hiace bus Makkah to Makkah Ziyarat",
                    "rent Toyota Hiace bus in Makkah Ziyarat",
                    "luxury SUV rental Makkah to Makkah Ziyarat",
                    "rent luxury SUV rental in Makkah Ziyarat",
                    "7 seater family van Makkah to Makkah Ziyarat",
                    "rent 7 seater family van in Makkah Ziyarat",
                    "11 passenger minibus Makkah to Makkah Ziyarat",
                    "rent 11 passenger minibus in Makkah Ziyarat",
                    "premium VIP car Makkah to Makkah Ziyarat",
                    "rent premium VIP car in Makkah Ziyarat",
                    "pilgrim transport Makkah to Makkah Ziyarat",
                    "umrah taxi company Makkah to Makkah Ziyarat",
                    "certified drivers Makkah to Makkah Ziyarat",
                    "ihram friendly Makkah to Makkah Ziyarat",
                    "saudi transport agency Makkah to Makkah Ziyarat",
                    "hajj cab service Makkah to Makkah Ziyarat",
                    "english speaking driver Makkah to Makkah Ziyarat",
                    "historical tour Makkah",
                    "Makkah historical tour taxi",
                    "islamic landmarks Makkah",
                    "Makkah islamic landmarks taxi",
                    "cave hira Makkah",
                    "Makkah cave hira taxi",
                    "mount uhud Makkah",
                    "Makkah mount uhud taxi",
                    "masjid quba Makkah",
                    "Makkah masjid quba taxi",
                    "private guide Makkah",
                    "Makkah private guide taxi",
                    "ziyarat package Makkah",
                    "Makkah ziyarat package taxi",
                    "jabal thawr Makkah",
                    "Makkah jabal thawr taxi",
                    "qiblatayn Makkah",
                    "Makkah qiblatayn taxi",
                    "seven mosques Makkah",
                    "Makkah seven mosques taxi"
                ]
            },
            "distance": "40 km",
            "time": "3-4 hrs",
            "baseRate": 250,
            "customRates": {
                "camry": 250,
                "hiace": 300,
                "gmc": 400,
                "starex": 250,
                "staria": 250,
                "coaster": 500
            }
        },
        {
            "id": "madinah-hotel-to-madinah-airport",
            "name": "Madinah Hotel to Madinah Airport",
            "slug": "madinah-hotel-to-airport",
            "seo": {
                "title": "Taxi Madinah Hotel to Airport | Departure Transfer | توصيل للمطار",
                "description": "Reliable pickup from your Madinah hotel to Prince Mohammad Bin Abdulaziz Airport (MED). Punctual service ensuring you reach on time.",
                "keywords": [
                    "Madinah hotel to airport taxi",
                    "taxi Madinah to airport price",
                    "Madinah departure transfer",
                    "MED airport drop off",
                    "توصيل من فندق المدينة للمطار",
                    "تاكسي مطار المدينة مغادرة",
                    "Madinah to Madinah Airport taxi",
                    "taxi from Madinah to Madinah Airport",
                    "Madinah to Madinah Airport fare",
                    "how much is taxi from Madinah to Madinah Airport",
                    "book cab Madinah",
                    "transportation to Madinah Airport",
                    "private car Madinah to Madinah Airport",
                    "book online Madinah",
                    "Madinah to Madinah Airport book online",
                    "cheap transport Madinah",
                    "Madinah to Madinah Airport cheap transport",
                    "affordable taxi Madinah",
                    "Madinah to Madinah Airport affordable taxi",
                    "VIP transfer Madinah",
                    "Madinah to Madinah Airport VIP transfer",
                    "luxury ride Madinah",
                    "Madinah to Madinah Airport luxury ride",
                    "private cab Madinah",
                    "Madinah to Madinah Airport private cab",
                    "reliable transportation Madinah",
                    "Madinah to Madinah Airport reliable transportation",
                    "family van hire Madinah",
                    "Madinah to Madinah Airport family van hire",
                    "group travel bus Madinah",
                    "Madinah to Madinah Airport group travel bus",
                    "24/7 service Madinah",
                    "Madinah to Madinah Airport 24/7 service",
                    "instant confirmation booking Madinah",
                    "Madinah to Madinah Airport instant confirmation booking",
                    "whatsapp reservation Madinah",
                    "Madinah to Madinah Airport whatsapp reservation",
                    "safe pilgrim travel Madinah",
                    "Madinah to Madinah Airport safe pilgrim travel",
                    "executive chauffeur Madinah",
                    "Madinah to Madinah Airport executive chauffeur",
                    "GMC Yukon XL Madinah to Madinah Airport",
                    "rent GMC Yukon XL in Madinah Airport",
                    "Hyundai Staria VIP Madinah to Madinah Airport",
                    "rent Hyundai Staria VIP in Madinah Airport",
                    "Toyota Camry sedan Madinah to Madinah Airport",
                    "rent Toyota Camry sedan in Madinah Airport",
                    "Toyota Hiace bus Madinah to Madinah Airport",
                    "rent Toyota Hiace bus in Madinah Airport",
                    "luxury SUV rental Madinah to Madinah Airport",
                    "rent luxury SUV rental in Madinah Airport",
                    "7 seater family van Madinah to Madinah Airport",
                    "rent 7 seater family van in Madinah Airport",
                    "11 passenger minibus Madinah to Madinah Airport",
                    "rent 11 passenger minibus in Madinah Airport",
                    "premium VIP car Madinah to Madinah Airport",
                    "rent premium VIP car in Madinah Airport",
                    "pilgrim transport Madinah to Madinah Airport",
                    "umrah taxi company Madinah to Madinah Airport",
                    "certified drivers Madinah to Madinah Airport",
                    "ihram friendly Madinah to Madinah Airport",
                    "saudi transport agency Madinah to Madinah Airport",
                    "hajj cab service Madinah to Madinah Airport",
                    "english speaking driver Madinah to Madinah Airport",
                    "Madinah airport transfer",
                    "airport transfer to Madinah Airport",
                    "Madinah meet and greet",
                    "meet and greet to Madinah Airport",
                    "Madinah terminal pickup",
                    "terminal pickup to Madinah Airport",
                    "Madinah KAIA",
                    "KAIA to Madinah Airport",
                    "Madinah MED",
                    "MED to Madinah Airport",
                    "Madinah airport dropoff",
                    "airport dropoff to Madinah Airport"
                ]
            },
            "distance": "20 km",
            "time": "25 min",
            "baseRate": 150,
            "customRates": {
                "camry": 150,
                "hiace": 250,
                "gmc": 300,
                "starex": 200,
                "staria": 250,
                "coaster": 400
            }
        },
        {
            "id": "6949b368a41f6410e88ed738",
            "name": "Madinah Airport to Madinah Hotel",
            "slug": "madinah-airport-to-hotel",
            "seo": {
                "title": "Taxi Madinah Airport to Hotel | Arrival Transfer | استقبال مطار المدينة",
                "description": "Direct transfer from Madinah Airport (MED) to your hotel. English/Urdu speaking drivers available. 24/7 flight monitoring and Meet & Greet.",
                "keywords": [
                    "Madinah airport to hotel taxi",
                    "taxi fare Madinah airport",
                    "Madinah arrival taxi",
                    "Madinah airport pickup",
                    "توصيل من مطار المدينة للفندق",
                    "استقبال مطار المدينة المنورة",
                    "Madinah Airport to Madinah taxi",
                    "taxi from Madinah Airport to Madinah",
                    "Madinah Airport to Madinah fare",
                    "how much is taxi from Madinah Airport to Madinah",
                    "book cab Madinah Airport",
                    "transportation to Madinah",
                    "private car Madinah Airport to Madinah",
                    "book online Madinah Airport",
                    "Madinah Airport to Madinah book online",
                    "cheap transport Madinah Airport",
                    "Madinah Airport to Madinah cheap transport",
                    "affordable taxi Madinah Airport",
                    "Madinah Airport to Madinah affordable taxi",
                    "VIP transfer Madinah Airport",
                    "Madinah Airport to Madinah VIP transfer",
                    "luxury ride Madinah Airport",
                    "Madinah Airport to Madinah luxury ride",
                    "private cab Madinah Airport",
                    "Madinah Airport to Madinah private cab",
                    "reliable transportation Madinah Airport",
                    "Madinah Airport to Madinah reliable transportation",
                    "family van hire Madinah Airport",
                    "Madinah Airport to Madinah family van hire",
                    "group travel bus Madinah Airport",
                    "Madinah Airport to Madinah group travel bus",
                    "24/7 service Madinah Airport",
                    "Madinah Airport to Madinah 24/7 service",
                    "instant confirmation booking Madinah Airport",
                    "Madinah Airport to Madinah instant confirmation booking",
                    "whatsapp reservation Madinah Airport",
                    "Madinah Airport to Madinah whatsapp reservation",
                    "safe pilgrim travel Madinah Airport",
                    "Madinah Airport to Madinah safe pilgrim travel",
                    "executive chauffeur Madinah Airport",
                    "Madinah Airport to Madinah executive chauffeur",
                    "GMC Yukon XL Madinah Airport to Madinah",
                    "rent GMC Yukon XL in Madinah",
                    "Hyundai Staria VIP Madinah Airport to Madinah",
                    "rent Hyundai Staria VIP in Madinah",
                    "Toyota Camry sedan Madinah Airport to Madinah",
                    "rent Toyota Camry sedan in Madinah",
                    "Toyota Hiace bus Madinah Airport to Madinah",
                    "rent Toyota Hiace bus in Madinah",
                    "luxury SUV rental Madinah Airport to Madinah",
                    "rent luxury SUV rental in Madinah",
                    "7 seater family van Madinah Airport to Madinah",
                    "rent 7 seater family van in Madinah",
                    "11 passenger minibus Madinah Airport to Madinah",
                    "rent 11 passenger minibus in Madinah",
                    "premium VIP car Madinah Airport to Madinah",
                    "rent premium VIP car in Madinah",
                    "pilgrim transport Madinah Airport to Madinah",
                    "umrah taxi company Madinah Airport to Madinah",
                    "certified drivers Madinah Airport to Madinah",
                    "ihram friendly Madinah Airport to Madinah",
                    "saudi transport agency Madinah Airport to Madinah",
                    "hajj cab service Madinah Airport to Madinah",
                    "english speaking driver Madinah Airport to Madinah",
                    "Madinah Airport airport transfer",
                    "airport transfer to Madinah",
                    "Madinah Airport meet and greet",
                    "meet and greet to Madinah",
                    "Madinah Airport terminal pickup",
                    "terminal pickup to Madinah",
                    "Madinah Airport KAIA",
                    "KAIA to Madinah",
                    "Madinah Airport MED",
                    "MED to Madinah",
                    "Madinah Airport airport dropoff",
                    "airport dropoff to Madinah"
                ]
            },
            "distance": "20 km",
            "time": "25 min",
            "baseRate": 120,
            "customRates": {
                "camry": 120,
                "hiace": 250,
                "gmc": 300,
                "starex": 200,
                "staria": 250,
                "coaster": 400
            }
        },
        {
            "id": "692db09934f15bc89b45a600",
            "name": "Madinah Hotel to Makkah Hotel",
            "slug": "madinah-to-makkah-taxi",
            "seo": {
                "title": "Madinah to Makkah Taxi | VIP Private Transfer | توصيل المدينة مكة",
                "description": "Book a comfortable ride from Madinah to Makkah. Features Miqat stop (Masjid Dhul Hulaifah), luxury AC cars, and experienced drivers. Best rates guaranteed.",
                "keywords": [
                    "Madinah to Makkah taxi",
                    "taxi from Madinah to Makkah",
                    "private car Madinah to Makkah",
                    "VIP transfer Madinah Makkah",
                    "taxi fare Madinah Makkah",
                    "توصيل من المدينة الى مكة",
                    "تاكسي المدينة مكة",
                    "سعر المشوار من المدينة لمكة",
                    "Madinah to Makkah fare",
                    "how much is taxi from Madinah to Makkah",
                    "book cab Madinah",
                    "transportation to Makkah",
                    "book online Madinah",
                    "Madinah to Makkah book online",
                    "cheap transport Madinah",
                    "Madinah to Makkah cheap transport",
                    "affordable taxi Madinah",
                    "Madinah to Makkah affordable taxi",
                    "VIP transfer Madinah",
                    "Madinah to Makkah VIP transfer",
                    "luxury ride Madinah",
                    "Madinah to Makkah luxury ride",
                    "private cab Madinah",
                    "Madinah to Makkah private cab",
                    "reliable transportation Madinah",
                    "Madinah to Makkah reliable transportation",
                    "family van hire Madinah",
                    "Madinah to Makkah family van hire",
                    "group travel bus Madinah",
                    "Madinah to Makkah group travel bus",
                    "24/7 service Madinah",
                    "Madinah to Makkah 24/7 service",
                    "instant confirmation booking Madinah",
                    "Madinah to Makkah instant confirmation booking",
                    "whatsapp reservation Madinah",
                    "Madinah to Makkah whatsapp reservation",
                    "safe pilgrim travel Madinah",
                    "Madinah to Makkah safe pilgrim travel",
                    "executive chauffeur Madinah",
                    "Madinah to Makkah executive chauffeur",
                    "GMC Yukon XL Madinah to Makkah",
                    "rent GMC Yukon XL in Makkah",
                    "Hyundai Staria VIP Madinah to Makkah",
                    "rent Hyundai Staria VIP in Makkah",
                    "Toyota Camry sedan Madinah to Makkah",
                    "rent Toyota Camry sedan in Makkah",
                    "Toyota Hiace bus Madinah to Makkah",
                    "rent Toyota Hiace bus in Makkah",
                    "luxury SUV rental Madinah to Makkah",
                    "rent luxury SUV rental in Makkah",
                    "7 seater family van Madinah to Makkah",
                    "rent 7 seater family van in Makkah",
                    "11 passenger minibus Madinah to Makkah",
                    "rent 11 passenger minibus in Makkah",
                    "premium VIP car Madinah to Makkah",
                    "rent premium VIP car in Makkah",
                    "pilgrim transport Madinah to Makkah",
                    "umrah taxi company Madinah to Makkah",
                    "certified drivers Madinah to Makkah",
                    "ihram friendly Madinah to Makkah",
                    "saudi transport agency Madinah to Makkah",
                    "hajj cab service Madinah to Makkah",
                    "english speaking driver Madinah to Makkah"
                ]
            },
            "distance": "450 km",
            "time": "4 hrs 30 min",
            "baseRate": 450,
            "customRates": {
                "camry": 450,
                "hiace": 550,
                "gmc": 900,
                "starex": 450,
                "staria": 450,
                "coaster": 900
            }
        },
        {
            "id": "jeddah-airport-to-madina-hotel",
            "name": "Jeddah Airport to Madinah Hotel",
            "slug": "jeddah-airport-to-madinah",
            "seo": {
                "title": "Taxi Jeddah Airport to Madinah | Direct Transfer | توصيل جدة المدينة",
                "description": "Travel directly from Jeddah Airport (KAIA) to Madinah Hotels. Comfortable, long-distance certified vehicles (GMC, Camry, Staria) for a smooth 4-hour journey.",
                "keywords": [
                    "Jeddah Airport to Madinah taxi",
                    "KAIA to Madinah taxi",
                    "taxi Jeddah to Madinah price",
                    "Jeddah to Madinah car rental",
                    "airport transfer Jeddah Madinah",
                    "توصيل من مطار جدة للمدينة",
                    "تاكسي جدة المدينة",
                    "سعر التوصيل من جدة للمدينة",
                    "taxi from Jeddah Airport to Madinah",
                    "Jeddah Airport to Madinah fare",
                    "how much is taxi from Jeddah Airport to Madinah",
                    "book cab Jeddah Airport",
                    "transportation to Madinah",
                    "private car Jeddah Airport to Madinah",
                    "book online Jeddah Airport",
                    "Jeddah Airport to Madinah book online",
                    "cheap transport Jeddah Airport",
                    "Jeddah Airport to Madinah cheap transport",
                    "affordable taxi Jeddah Airport",
                    "Jeddah Airport to Madinah affordable taxi",
                    "VIP transfer Jeddah Airport",
                    "Jeddah Airport to Madinah VIP transfer",
                    "luxury ride Jeddah Airport",
                    "Jeddah Airport to Madinah luxury ride",
                    "private cab Jeddah Airport",
                    "Jeddah Airport to Madinah private cab",
                    "reliable transportation Jeddah Airport",
                    "Jeddah Airport to Madinah reliable transportation",
                    "family van hire Jeddah Airport",
                    "Jeddah Airport to Madinah family van hire",
                    "group travel bus Jeddah Airport",
                    "Jeddah Airport to Madinah group travel bus",
                    "24/7 service Jeddah Airport",
                    "Jeddah Airport to Madinah 24/7 service",
                    "instant confirmation booking Jeddah Airport",
                    "Jeddah Airport to Madinah instant confirmation booking",
                    "whatsapp reservation Jeddah Airport",
                    "Jeddah Airport to Madinah whatsapp reservation",
                    "safe pilgrim travel Jeddah Airport",
                    "Jeddah Airport to Madinah safe pilgrim travel",
                    "executive chauffeur Jeddah Airport",
                    "Jeddah Airport to Madinah executive chauffeur",
                    "GMC Yukon XL Jeddah Airport to Madinah",
                    "rent GMC Yukon XL in Madinah",
                    "Hyundai Staria VIP Jeddah Airport to Madinah",
                    "rent Hyundai Staria VIP in Madinah",
                    "Toyota Camry sedan Jeddah Airport to Madinah",
                    "rent Toyota Camry sedan in Madinah",
                    "Toyota Hiace bus Jeddah Airport to Madinah",
                    "rent Toyota Hiace bus in Madinah",
                    "luxury SUV rental Jeddah Airport to Madinah",
                    "rent luxury SUV rental in Madinah",
                    "7 seater family van Jeddah Airport to Madinah",
                    "rent 7 seater family van in Madinah",
                    "11 passenger minibus Jeddah Airport to Madinah",
                    "rent 11 passenger minibus in Madinah",
                    "premium VIP car Jeddah Airport to Madinah",
                    "rent premium VIP car in Madinah",
                    "pilgrim transport Jeddah Airport to Madinah",
                    "umrah taxi company Jeddah Airport to Madinah",
                    "certified drivers Jeddah Airport to Madinah",
                    "ihram friendly Jeddah Airport to Madinah",
                    "saudi transport agency Jeddah Airport to Madinah",
                    "hajj cab service Jeddah Airport to Madinah",
                    "english speaking driver Jeddah Airport to Madinah",
                    "Jeddah Airport airport transfer",
                    "airport transfer to Madinah",
                    "Jeddah Airport meet and greet",
                    "meet and greet to Madinah",
                    "Jeddah Airport terminal pickup",
                    "terminal pickup to Madinah",
                    "Jeddah Airport KAIA",
                    "KAIA to Madinah",
                    "Jeddah Airport MED",
                    "MED to Madinah",
                    "Jeddah Airport airport dropoff",
                    "airport dropoff to Madinah"
                ]
            },
            "distance": "400 km",
            "time": "4 hrs",
            "baseRate": 500,
            "customRates": {
                "camry": 500,
                "hiace": 600,
                "gmc": 1000,
                "starex": 500,
                "staria": 550,
                "coaster": 1100
            }
        },
        {
            "id": "jeddah-airport-to-jeddah-hotel",
            "name": "Jeddah Airport to Jeddah Hotel",
            "slug": "jeddah-airport-transfer",
            "seo": {
                "title": "Jeddah Airport Taxi to Jeddah Hotel | KAIA Transfer | تاكسي مطار جدة",
                "description": "Fast and affordable taxi from Jeddah Airport (KAIA) to any hotel or district in Jeddah (Al Balad, Corniche, Obhur). Meet and greet included.",
                "keywords": [
                    "Jeddah airport taxi",
                    "Taxi to Jeddah hotel",
                    "KAIA airport transfer",
                    "Jeddah city transfer",
                    "taxi from airport to Jeddah city",
                    "توصيل من مطار جدة للفندق",
                    "تاكسي داخل جدة",
                    "توصيل جدة البلد",
                    "Jeddah Airport to Jeddah taxi",
                    "taxi from Jeddah Airport to Jeddah",
                    "Jeddah Airport to Jeddah fare",
                    "how much is taxi from Jeddah Airport to Jeddah",
                    "book cab Jeddah Airport",
                    "transportation to Jeddah",
                    "private car Jeddah Airport to Jeddah",
                    "book online Jeddah Airport",
                    "Jeddah Airport to Jeddah book online",
                    "cheap transport Jeddah Airport",
                    "Jeddah Airport to Jeddah cheap transport",
                    "affordable taxi Jeddah Airport",
                    "Jeddah Airport to Jeddah affordable taxi",
                    "VIP transfer Jeddah Airport",
                    "Jeddah Airport to Jeddah VIP transfer",
                    "luxury ride Jeddah Airport",
                    "Jeddah Airport to Jeddah luxury ride",
                    "private cab Jeddah Airport",
                    "Jeddah Airport to Jeddah private cab",
                    "reliable transportation Jeddah Airport",
                    "Jeddah Airport to Jeddah reliable transportation",
                    "family van hire Jeddah Airport",
                    "Jeddah Airport to Jeddah family van hire",
                    "group travel bus Jeddah Airport",
                    "Jeddah Airport to Jeddah group travel bus",
                    "24/7 service Jeddah Airport",
                    "Jeddah Airport to Jeddah 24/7 service",
                    "instant confirmation booking Jeddah Airport",
                    "Jeddah Airport to Jeddah instant confirmation booking",
                    "whatsapp reservation Jeddah Airport",
                    "Jeddah Airport to Jeddah whatsapp reservation",
                    "safe pilgrim travel Jeddah Airport",
                    "Jeddah Airport to Jeddah safe pilgrim travel",
                    "executive chauffeur Jeddah Airport",
                    "Jeddah Airport to Jeddah executive chauffeur",
                    "GMC Yukon XL Jeddah Airport to Jeddah",
                    "rent GMC Yukon XL in Jeddah",
                    "Hyundai Staria VIP Jeddah Airport to Jeddah",
                    "rent Hyundai Staria VIP in Jeddah",
                    "Toyota Camry sedan Jeddah Airport to Jeddah",
                    "rent Toyota Camry sedan in Jeddah",
                    "Toyota Hiace bus Jeddah Airport to Jeddah",
                    "rent Toyota Hiace bus in Jeddah",
                    "luxury SUV rental Jeddah Airport to Jeddah",
                    "rent luxury SUV rental in Jeddah",
                    "7 seater family van Jeddah Airport to Jeddah",
                    "rent 7 seater family van in Jeddah",
                    "11 passenger minibus Jeddah Airport to Jeddah",
                    "rent 11 passenger minibus in Jeddah",
                    "premium VIP car Jeddah Airport to Jeddah",
                    "rent premium VIP car in Jeddah",
                    "pilgrim transport Jeddah Airport to Jeddah",
                    "umrah taxi company Jeddah Airport to Jeddah",
                    "certified drivers Jeddah Airport to Jeddah",
                    "ihram friendly Jeddah Airport to Jeddah",
                    "saudi transport agency Jeddah Airport to Jeddah",
                    "hajj cab service Jeddah Airport to Jeddah",
                    "english speaking driver Jeddah Airport to Jeddah",
                    "Jeddah Airport airport transfer",
                    "airport transfer to Jeddah",
                    "Jeddah Airport meet and greet",
                    "meet and greet to Jeddah",
                    "Jeddah Airport terminal pickup",
                    "terminal pickup to Jeddah",
                    "Jeddah Airport KAIA",
                    "KAIA to Jeddah",
                    "Jeddah Airport MED",
                    "MED to Jeddah",
                    "Jeddah Airport airport dropoff",
                    "airport dropoff to Jeddah"
                ]
            },
            "distance": "30 km",
            "time": "30 min",
            "baseRate": 200,
            "customRates": {
                "camry": 200,
                "hiace": 250,
                "gmc": 350,
                "starex": 250,
                "staria": 250,
                "coaster": 450
            }
        },
        {
            "id": "makkah-hotel-to-madina-airport",
            "name": "Makkah Hotel to Madinah Airport",
            "slug": "makkah-to-madinah-airport",
            "seo": {
                "title": "Taxi Makkah to Madinah Airport | Long Distance Cab | توصيل مكة مطار المدينة",
                "description": "Direct taxi from Makkah to Madinah Airport (MED). Ensure you reach your flight on time with our reliable intercity service. comfortable 5-hour ride.",
                "keywords": [
                    "Makkah to Madinah airport taxi",
                    "Makkah to MED transfer",
                    "taxi Makkah to Madinah airport price",
                    "airport transfer Makkah to Medinah",
                    "توصيل من مكة لمطار المدينة",
                    "نقل مكة مطار الأمير محمد",
                    "Makkah to Madinah Airport taxi",
                    "taxi from Makkah to Madinah Airport",
                    "Makkah to Madinah Airport fare",
                    "how much is taxi from Makkah to Madinah Airport",
                    "book cab Makkah",
                    "transportation to Madinah Airport",
                    "private car Makkah to Madinah Airport",
                    "book online Makkah",
                    "Makkah to Madinah Airport book online",
                    "cheap transport Makkah",
                    "Makkah to Madinah Airport cheap transport",
                    "affordable taxi Makkah",
                    "Makkah to Madinah Airport affordable taxi",
                    "VIP transfer Makkah",
                    "Makkah to Madinah Airport VIP transfer",
                    "luxury ride Makkah",
                    "Makkah to Madinah Airport luxury ride",
                    "private cab Makkah",
                    "Makkah to Madinah Airport private cab",
                    "reliable transportation Makkah",
                    "Makkah to Madinah Airport reliable transportation",
                    "family van hire Makkah",
                    "Makkah to Madinah Airport family van hire",
                    "group travel bus Makkah",
                    "Makkah to Madinah Airport group travel bus",
                    "24/7 service Makkah",
                    "Makkah to Madinah Airport 24/7 service",
                    "instant confirmation booking Makkah",
                    "Makkah to Madinah Airport instant confirmation booking",
                    "whatsapp reservation Makkah",
                    "Makkah to Madinah Airport whatsapp reservation",
                    "safe pilgrim travel Makkah",
                    "Makkah to Madinah Airport safe pilgrim travel",
                    "executive chauffeur Makkah",
                    "Makkah to Madinah Airport executive chauffeur",
                    "GMC Yukon XL Makkah to Madinah Airport",
                    "rent GMC Yukon XL in Madinah Airport",
                    "Hyundai Staria VIP Makkah to Madinah Airport",
                    "rent Hyundai Staria VIP in Madinah Airport",
                    "Toyota Camry sedan Makkah to Madinah Airport",
                    "rent Toyota Camry sedan in Madinah Airport",
                    "Toyota Hiace bus Makkah to Madinah Airport",
                    "rent Toyota Hiace bus in Madinah Airport",
                    "luxury SUV rental Makkah to Madinah Airport",
                    "rent luxury SUV rental in Madinah Airport",
                    "7 seater family van Makkah to Madinah Airport",
                    "rent 7 seater family van in Madinah Airport",
                    "11 passenger minibus Makkah to Madinah Airport",
                    "rent 11 passenger minibus in Madinah Airport",
                    "premium VIP car Makkah to Madinah Airport",
                    "rent premium VIP car in Madinah Airport",
                    "pilgrim transport Makkah to Madinah Airport",
                    "umrah taxi company Makkah to Madinah Airport",
                    "certified drivers Makkah to Madinah Airport",
                    "ihram friendly Makkah to Madinah Airport",
                    "saudi transport agency Makkah to Madinah Airport",
                    "hajj cab service Makkah to Madinah Airport",
                    "english speaking driver Makkah to Madinah Airport",
                    "Makkah airport transfer",
                    "airport transfer to Madinah Airport",
                    "Makkah meet and greet",
                    "meet and greet to Madinah Airport",
                    "Makkah terminal pickup",
                    "terminal pickup to Madinah Airport",
                    "Makkah KAIA",
                    "KAIA to Madinah Airport",
                    "Makkah MED",
                    "MED to Madinah Airport",
                    "Makkah airport dropoff",
                    "airport dropoff to Madinah Airport"
                ]
            },
            "distance": "460 km",
            "time": "5 hrs",
            "baseRate": 600,
            "customRates": {
                "camry": 600,
                "hiace": 700,
                "gmc": 1100,
                "starex": 650,
                "staria": 650,
                "coaster": 1200
            }
        },
        {
            "id": "madina-hotel-to-jeddah-hotel",
            "name": "Madinah Hotel to Jeddah Hotel",
            "slug": "madinah-to-jeddah-taxi",
            "seo": {
                "title": "Taxi Madinah to Jeddah | Private Intercity Transfer | توصيل المدينة جدة",
                "description": "Travel from Madinah to Jeddah in comfort. Ideal for post-Umrah stays or catchments. Professional drivers familiar with the migration highway route.",
                "keywords": [
                    "Madinah to Jeddah taxi",
                    "car rental Madinah to Jeddah",
                    "taxi fare Madinah to Jeddah",
                    "private transport Madinah Jeddah",
                    "توصيل من المدينة الى جدة",
                    "سعر التاكسي من المدينة لجدة",
                    "نقل عفش المدينة جدة",
                    "taxi from Madinah to Jeddah",
                    "Madinah to Jeddah fare",
                    "how much is taxi from Madinah to Jeddah",
                    "book cab Madinah",
                    "transportation to Jeddah",
                    "private car Madinah to Jeddah",
                    "book online Madinah",
                    "Madinah to Jeddah book online",
                    "cheap transport Madinah",
                    "Madinah to Jeddah cheap transport",
                    "affordable taxi Madinah",
                    "Madinah to Jeddah affordable taxi",
                    "VIP transfer Madinah",
                    "Madinah to Jeddah VIP transfer",
                    "luxury ride Madinah",
                    "Madinah to Jeddah luxury ride",
                    "private cab Madinah",
                    "Madinah to Jeddah private cab",
                    "reliable transportation Madinah",
                    "Madinah to Jeddah reliable transportation",
                    "family van hire Madinah",
                    "Madinah to Jeddah family van hire",
                    "group travel bus Madinah",
                    "Madinah to Jeddah group travel bus",
                    "24/7 service Madinah",
                    "Madinah to Jeddah 24/7 service",
                    "instant confirmation booking Madinah",
                    "Madinah to Jeddah instant confirmation booking",
                    "whatsapp reservation Madinah",
                    "Madinah to Jeddah whatsapp reservation",
                    "safe pilgrim travel Madinah",
                    "Madinah to Jeddah safe pilgrim travel",
                    "executive chauffeur Madinah",
                    "Madinah to Jeddah executive chauffeur",
                    "GMC Yukon XL Madinah to Jeddah",
                    "rent GMC Yukon XL in Jeddah",
                    "Hyundai Staria VIP Madinah to Jeddah",
                    "rent Hyundai Staria VIP in Jeddah",
                    "Toyota Camry sedan Madinah to Jeddah",
                    "rent Toyota Camry sedan in Jeddah",
                    "Toyota Hiace bus Madinah to Jeddah",
                    "rent Toyota Hiace bus in Jeddah",
                    "luxury SUV rental Madinah to Jeddah",
                    "rent luxury SUV rental in Jeddah",
                    "7 seater family van Madinah to Jeddah",
                    "rent 7 seater family van in Jeddah",
                    "11 passenger minibus Madinah to Jeddah",
                    "rent 11 passenger minibus in Jeddah",
                    "premium VIP car Madinah to Jeddah",
                    "rent premium VIP car in Jeddah",
                    "pilgrim transport Madinah to Jeddah",
                    "umrah taxi company Madinah to Jeddah",
                    "certified drivers Madinah to Jeddah",
                    "ihram friendly Madinah to Jeddah",
                    "saudi transport agency Madinah to Jeddah",
                    "hajj cab service Madinah to Jeddah",
                    "english speaking driver Madinah to Jeddah"
                ]
            },
            "distance": "400 km",
            "time": "4 hrs",
            "baseRate": 500,
            "customRates": {
                "camry": 500,
                "hiace": 600,
                "gmc": 1000,
                "starex": 500,
                "staria": 550,
                "coaster": 1100
            }
        }
    ],
    "vehicles": [
        {
            "id": "camry",
            "name": "Toyota Camry",
            "slug": "toyota-camry",
            "seo": {
                "title": "Toyota Camry Taxi Makkah & Jeddah | Economy Choice | كامري",
                "description": "Book Toyota Camry taxi for Umrah. Affordable, comfortable, and reliable for small families (3-4 pax). Best economy option for Jeddah to Makkah transfers.",
                "keywords": [
                    "Toyota Camry Makkah",
                    "Camry taxi Jeddah",
                    "economy umrah transport",
                    "cheap car rental Makkah",
                    "camry price jeddah makkah",
                    "كامري توصيل مكة",
                    "تاكسي كامري جدة"
                ]
            },
            "capacity": "4 Seater",
            "multiplier": 1,
            "features": [
                "Air Conditioning",
                "Comfortable Seating",
                "USB Charging",
                "Perfect for couples"
            ],
            "luggage": "2 Large Suitcases"
        },
        {
            "id": "gmc",
            "name": "GMC Yukon",
            "slug": "gmc-yukon-at4",
            "seo": {
                "title": "GMC Yukon Rental Makkah | VIP Umrah Transport | جمس يوكن 2025",
                "description": "Luxury GMC Yukon XL 2025 rental in Makkah. 7-seater SUV for VIP Jeddah airport transfers and Makkah-Madinah travel. Ultimate comfort and style.",
                "keywords": [
                    "GMC Yukon Makkah",
                    "GMC Yukon taxi Jeddah",
                    "VIP transport Umrah",
                    "luxury SUV Saudi Arabia",
                    "GMC XL rental Makkah",
                    "جمس يوكن توصيل",
                    "يوكن xl مكة",
                    "نقل vip جدة"
                ]
            },
            "capacity": "7 Seater",
            "multiplier": 1.5,
            "features": [
                "Luxury Leather Seats",
                "Premium Sound",
                "Extra Legroom",
                "Privacy Tint",
                "Dual AC"
            ],
            "luggage": "5 Large Suitcases"
        },
        {
            "id": "staria",
            "name": "Hyundai Staria",
            "slug": "hyundai-staria",
            "seo": {
                "title": "Hyundai Staria Taxi Makkah | 2025 Luxury Van | ستاريا",
                "description": "Ride in the futuristic Hyundai Staria. Spacious 7-seater van perfect for families. Modern interior, panoramic windows, and pilot seats. Jeddah & Makkah.",
                "keywords": [
                    "Hyundai Staria Makkah",
                    "Staria taxi Jeddah",
                    "family van rental Umrah",
                    "luxury van Saudi Arabia",
                    "Staria 2025 Makkah",
                    "هيونداي ستاريا نقل",
                    "فان عائلي مكة"
                ]
            },
            "capacity": "7 Seater",
            "multiplier": 1.3,
            "features": [
                "Modern Design",
                "Panoramic Windows",
                "Premium Comfort",
                "Pilot Seats",
                "USB-C Ports"
            ],
            "luggage": "4 Large Suitcases"
        },
        {
            "id": "starex",
            "name": "Hyundai Starex",
            "slug": "hyundai-starex",
            "seo": {
                "title": "Hyundai H1 Starex Taxi Makkah | Family Van | اتش ون",
                "description": "Reliable Hyundai H1 (Starex) van for rent. Affordable family transport for Jeddah to Makkah/Madinah. 7+ passengers with good luggage space.",
                "keywords": [
                    "Hyundai H1 Makkah",
                    "Starex taxi Jeddah",
                    "cheap family van Umrah",
                    "H1 bus rental",
                    "Hyundai H1 price",
                    "اتش ون توصيل",
                    "هيونداي h1 مكة"
                ]
            },
            "capacity": "7 Seater",
            "multiplier": 1.2,
            "features": [
                "Spacious Interior",
                "AC Vents for Rear",
                "Sliding Doors",
                "Budget Friendly"
            ],
            "luggage": "4 Large Suitcases"
        },
        {
            "id": "hiace",
            "name": "Toyota Hiace",
            "slug": "toyota-hiace",
            "seo": {
                "title": "Toyota Hiace Bus Rental Makkah | 10-14 Seater | باص هايس",
                "description": "Rent Toyota Hiace 14-seater (used as 10-seater for comfort) in Makkah/Jeddah. Ideal for small groups and large families with luggage. Reliable group transport.",
                "keywords": [
                    "Toyota Hiace Makkah",
                    "10 seater taxi Jeddah",
                    "small bus rental Umrah",
                    "Hiace van rental",
                    "group transport Makkah",
                    "باص هايس توصيل",
                    "هايس 10 راكب",
                    "نقل جماعي مكة"
                ]
            },
            "capacity": "10/11 Seater",
            "multiplier": 1.6,
            "features": [
                "High Roof",
                "Individual Seats",
                "Ample Luggage Space",
                "Group Travel"
            ],
            "luggage": "8 Large Suitcases"
        },
        {
            "id": "coaster",
            "name": "Toyota Coaster",
            "slug": "toyota-coaster",
            "seo": {
                "title": "Toyota Coaster Bus Makkah | 20-25 Pax Transport | باص كوستر",
                "description": "Toyota Coaster bus rental for Umrah groups. Comfortable 21+ seater mini bus for Jeddah to Makkah transfers and Ziyarat. Professional drivers.",
                "keywords": [
                    "Toyota Coaster Makkah",
                    "bus rental Jeddah",
                    "group transport Umrah",
                    "Coaster bus price",
                    "25 seater bus Makkah",
                    "باص كوستر ايجار",
                    "نقل حملات مكة",
                    "باص كوستر جدة"
                ]
            },
            "capacity": "21 Seater",
            "multiplier": 2.5,
            "features": [
                "Microphone System",
                "Curtains",
                "Reclining Seats",
                "Large Windows"
            ],
            "luggage": "15 Large Suitcases"
        }
    ]
}